monpackage_addition/__init__.py
monpackage_addition/cli.py
monpackage_addition/core.py
monpackage_addition-0.3.0.dist-info/METADATA
monpackage_addition-0.3.0.dist-info/WHEEL
monpackage_addition-0.3.0.dist-info/entry_points.txt
monpackage_addition-0.3.0.dist-info/top_level.txt
monpackage_addition-0.3.0.dist-info/RECORD
