Metadata-Version: 2.4
Name: monpackage-addition
Version: 0.3.0
Summary: Package avec addition et CLI
Author: ParfaiteSekongo
Author-email: p88971582@gmail.com
License: MIT
Classifier: Programming Language :: Python :: 3
Requires-Python: >=3.6
Dynamic: author
Dynamic: author-email
Dynamic: classifier
Dynamic: description
Dynamic: description-content-type
Dynamic: license
Dynamic: requires-python
Dynamic: summary
